hotline/__init__.py
hotline/anim.py
hotline/app.py
hotline/command.py
hotline/constant.py
hotline/context.py
hotline/contexts/__init__.py
hotline/contexts/bare.py
hotline/contexts/linux.py
hotline/contexts/mac.py
hotline/contexts/maya.py
hotline/contexts/nuke.py
hotline/contexts/win.py
hotline/history.py
hotline/mode.py
hotline/renamer.py
hotline/styles/__init__.py
hotline/styles/dark.css
hotline/styles/light.css
hotline/styles/maya.css
hotline/tests/__init__.py
hotline/tests/__main__.py
hotline/tests/test_renamer.py
hotline/utils.py
hotline/vendor/__init__.py
hotline/vendor/Qt.py
hotline/widgets.py
hotline-0.8.0.dist-info/LICENSE
hotline-0.8.0.dist-info/WHEEL
hotline-0.8.0.dist-info/METADATA
hotline-0.8.0.dist-info/RECORD
