Metadata-Version: 2.1
Name: hotline
Version: 0.8.0
Summary: Sublime text like Qt Command Palette
License: MIT
Author: Dan Bradham
Author-email: danielbradham@gmail.com
Requires-Python: >=3.6,<4.0
Classifier: License :: OSI Approved :: MIT License
Classifier: Programming Language :: Python :: 3
Classifier: Programming Language :: Python :: 3.6
Classifier: Programming Language :: Python :: 3.7
Classifier: Programming Language :: Python :: 3.8
Classifier: Programming Language :: Python :: 3.9
Requires-Dist: PySide2 (>=5.14.2,<6.0.0)
Requires-Dist: keyboard (>=0.13.5,<0.14.0)
